LICENSE
README.md
spylog/__init__.py
spylog/config.py
spylog/main.py
spylog/validator.py
spylog-0.1.3.dist-info/LICENSE
spylog-0.1.3.dist-info/METADATA
spylog-0.1.3.dist-info/WHEEL
spylog-0.1.3.dist-info/entry_points.txt
spylog-0.1.3.dist-info/RECORD
