Metadata-Version: 2.1
Name: spylog
Version: 0.1.3
Summary: Python Validator Proxy - waliduje pliki Python przed uruchomieniem
Home-page: https://github.com/your-username/spylog
License: MIT
Keywords: python,validator,security,syntax,checker,proxy
Author: Spylog Team
Author-email: spylog@example.com
Maintainer: Spylog Team
Maintainer-email: spylog@example.com
Requires-Python: >=3.8.1,<4.0
Classifier: Development Status :: 4 - Beta
Classifier: Environment :: Console
Classifier: Intended Audience :: Developers
Classifier: License :: OSI Approved :: Apache Software License
Classifier: License :: OSI Approved :: MIT License
Classifier: Operating System :: OS Independent
Classifier: Programming Language :: Python :: 3
Classifier: Programming Language :: Python :: 3.9
Classifier: Programming Language :: Python :: 3.10
Classifier: Programming Language :: Python :: 3.11
Classifier: Programming Language :: Python :: 3.12
Classifier: Programming Language :: Python :: 3.13
Classifier: Programming Language :: Python :: 3.8
Classifier: Topic :: Software Development :: Quality Assurance
Classifier: Topic :: Software Development :: Testing
Requires-Dist: docutils (>=0.19,<0.21.0)
Project-URL: Documentation, https://github.com/your-username/spylog#readme
Project-URL: Repository, https://github.com/your-username/spylog
